cc_reproject/.DS_Store
cc_reproject/.version
cc_reproject/__init__.py
cc_reproject/geo.py
cc_reproject/tools.py
cc_reproject/warp.py
cc_reproject/__pycache__/__init__.cpython-38.pyc
cc_reproject/__pycache__/cc_reproject.cpython-38.pyc
cc_reproject/__pycache__/geo.cpython-38.pyc
cc_reproject/__pycache__/tools.cpython-38.pyc
cc_reproject/__pycache__/warp.cpython-38.pyc
cc_reproject/resources/elev_rgb2.tif
cc_reproject/tests/test_warp.py
cc_reproject/tests/__pycache__/test_warp.cpython-38-pytest-6.2.3.pyc
cc_reproject/tests/__pycache__/test_warp.cpython-38.pyc
gdal_dask_reproject-0.0.51.dist-info/LICENSE
gdal_dask_reproject-0.0.51.dist-info/METADATA
gdal_dask_reproject-0.0.51.dist-info/WHEEL
gdal_dask_reproject-0.0.51.dist-info/top_level.txt
gdal_dask_reproject-0.0.51.dist-info/RECORD
